goiam/__init__.py
goiam/models.py
goiam/service.py
goiam/service_impl.py
goiam_python-0.3.0.dist-info/licenses/LICENSE
goiam_python-0.3.0.dist-info/METADATA
goiam_python-0.3.0.dist-info/WHEEL
goiam_python-0.3.0.dist-info/top_level.txt
goiam_python-0.3.0.dist-info/RECORD
