Metadata-Version: 2.4
Name: goiam-python
Version: 0.3.0
Summary: Python SDK for Go IAM - A lightweight Identity and Access Management server
Author-email: melvinodsa <melvinodsa@gmail.com>
Maintainer-email: melvinodsa <melvinodsa@gmail.com>
License: MIT License
Project-URL: Homepage, https://github.com/melvinodsa/go-iam-sdk
Project-URL: Repository, https://github.com/melvinodsa/go-iam-sdk.git
Project-URL: Documentation, https://github.com/melvinodsa/go-iam-sdk/tree/main/python
Project-URL: Issues, https://github.com/melvinodsa/go-iam-sdk/issues
Keywords: iam,authentication,authorization,golang,python,sdk
Classifier: Development Status :: 3 - Alpha
Classifier: Intended Audience :: Developers
Classifier: Programming Language :: Python :: 3
Classifier: Programming Language :: Python :: 3.8
Classifier: Programming Language :: Python :: 3.9
Classifier: Programming Language :: Python :: 3.10
Classifier: Programming Language :: Python :: 3.11
Classifier: Programming Language :: Python :: 3.12
Classifier: Topic :: Software Development :: Libraries :: Python Modules
Classifier: Topic :: System :: Systems Administration :: Authentication/Directory
Requires-Python: >=3.8
License-File: LICENSE
Requires-Dist: requests>=2.25.0
Provides-Extra: dev
Requires-Dist: pytest>=6.0; extra == "dev"
Requires-Dist: pytest-cov>=2.0; extra == "dev"
Requires-Dist: pytest-xdist>=2.0; extra == "dev"
Requires-Dist: pytest-mock>=3.0; extra == "dev"
Requires-Dist: black>=21.0; extra == "dev"
Requires-Dist: flake8>=3.8; extra == "dev"
Requires-Dist: mypy>=0.910; extra == "dev"
Requires-Dist: pylint>=2.12; extra == "dev"
Requires-Dist: isort>=5.0; extra == "dev"
Requires-Dist: bandit>=1.7; extra == "dev"
Requires-Dist: safety>=2.0; extra == "dev"
Requires-Dist: build>=0.7; extra == "dev"
Requires-Dist: twine>=4.0; extra == "dev"
Requires-Dist: check-manifest>=0.47; extra == "dev"
Dynamic: license-file
